simpleHarmony/__init__.py
simpleHarmony/simpleHarmony.py
simpleHarmony-0.1.0.dist-info/LICENSE
simpleHarmony-0.1.0.dist-info/METADATA
simpleHarmony-0.1.0.dist-info/WHEEL
simpleHarmony-0.1.0.dist-info/top_level.txt
simpleHarmony-0.1.0.dist-info/RECORD
