Metadata-Version: 2.1
Name: simpleHarmony
Version: 0.1.0
Summary: A Sage package for finding discrete harmonic representatives on simplicial complexes.
Home-page: https://github.com/prismika/simpleHarmony
Author: Brantley Vose
Author-email: brantmv@gmail.com
License: UNKNOWN
Platform: UNKNOWN
Classifier: Programming Language :: Python :: 3
Classifier: License :: OSI Approved :: MIT License
Classifier: Operating System :: OS Independent
Requires-Python: >=3.6
License-File: LICENSE
